MANIFEST.in
README.md
quicktest.py
settings_test.py
setup.py
django_facebook_pages.egg-info/PKG-INFO
django_facebook_pages.egg-info/SOURCES.txt
django_facebook_pages.egg-info/dependency_links.txt
django_facebook_pages.egg-info/not-zip-safe
django_facebook_pages.egg-info/requires.txt
django_facebook_pages.egg-info/top_level.txt
facebook_pages/__init__.py
facebook_pages/__init__.pyc
facebook_pages/admin.py
facebook_pages/admin.pyc
facebook_pages/factories.py
facebook_pages/factories.pyc
facebook_pages/mixins.py
facebook_pages/mixins.pyc
facebook_pages/models.py
facebook_pages/models.pyc
facebook_pages/parser.py
facebook_pages/parser.pyc
facebook_pages/tests.py
facebook_pages/tests.pyc
facebook_pages/migrations/0001_initial.py
facebook_pages/migrations/0001_initial.pyc
facebook_pages/migrations/0002_auto__del_post__del_postowner__del_unique_postowner_post_owner_content.py
facebook_pages/migrations/0003_auto__add_field_page_posts_count.py
facebook_pages/migrations/0004_auto__add_field_page_products__add_field_page_description__chg_field_p.py
facebook_pages/migrations/0004_auto__add_field_page_products__add_field_page_description__chg_field_p.pyc
facebook_pages/migrations/0005_auto__chg_field_page_website.py
facebook_pages/migrations/0006_auto__chg_field_page_link.py
facebook_pages/migrations/0007_auto__del_field_page_likes__del_field_page_checkins__add_field_page_li.py
facebook_pages/migrations/0008_auto__chg_field_page_phone.py
facebook_pages/migrations/__init__.py
facebook_pages/migrations/__init__.pyc